{
  "canonical_move": {
    "actualDistance": null,
    "captureChain": null,
    "captureTarget": null,
    "capturedStacks": null,
    "claimedTerritory": null,
    "collapsedMarkers": null,
    "disconnectedRegions": null,
    "eliminatedRings": null,
    "formedLines": null,
    "from": {
      "x": 3,
      "y": 1,
      "z": -4
    },
    "id": "simulated",
    "markerLeft": null,
    "minimumDistance": null,
    "moveNumber": 48,
    "overtakenRings": null,
    "placedOnStack": null,
    "placementCount": null,
    "player": 2,
    "stackMoved": null,
    "thinkTime": 0,
    "timestamp": "2025-12-04T21:53:44.287360",
    "to": {
      "x": -10,
      "y": 1,
      "z": 9
    },
    "type": "move_stack"
  },
  "canonical_move_index": 47,
  "db_path": "/Users/armand/Development/RingRift/ai-service/data/games/selfplay_hexagonal_2p.db",
  "diverged_at": 48,
  "game_id": "41f15516-0020-4579-8837-ba528e369f96",
  "mismatch_context": "post_move",
  "mismatch_kinds": ["current_player", "current_phase"],
  "python_summary": {
    "current_phase": "ring_placement",
    "current_player": 1,
    "game_status": "active",
    "move_index": 47,
    "state_hash": "10b4d5b472a432e2"
  },
  "total_moves_python": 214,
  "total_moves_ts": 214,
  "ts_summary": {
    "current_phase": "movement",
    "current_player": 2,
    "game_status": "active",
    "move_index": 48,
    "state_hash": "5d2f68500bf1a90d"
  }
}
