{
  "canonical_move": {
    "actualDistance": null,
    "captureChain": null,
    "captureTarget": null,
    "capturedStacks": null,
    "claimedTerritory": null,
    "collapsedMarkers": null,
    "disconnectedRegions": null,
    "eliminatedRings": null,
    "formedLines": null,
    "from": {
      "x": 1,
      "y": 6,
      "z": null
    },
    "id": "simulated",
    "markerLeft": null,
    "minimumDistance": null,
    "moveNumber": 60,
    "overtakenRings": null,
    "placedOnStack": null,
    "placementCount": null,
    "player": 2,
    "stackMoved": null,
    "thinkTime": 0,
    "timestamp": "2025-12-04T21:22:16.608778",
    "to": {
      "x": 4,
      "y": 6,
      "z": null
    },
    "type": "move_stack"
  },
  "canonical_move_index": 59,
  "db_path": "/Users/armand/Development/RingRift/ai-service/data/games/selfplay_square8_2p.db",
  "diverged_at": 60,
  "game_id": "913a2906-06b3-4309-8f58-77c394225780",
  "mismatch_context": "post_move",
  "mismatch_kinds": ["current_player"],
  "python_summary": {
    "current_phase": "line_processing",
    "current_player": 2,
    "game_status": "active",
    "move_index": 59,
    "state_hash": "e3c377e8bf8ddd0b"
  },
  "total_moves_python": 73,
  "total_moves_ts": 73,
  "ts_summary": {
    "current_phase": "line_processing",
    "current_player": 1,
    "game_status": "active",
    "move_index": 60,
    "state_hash": "8837baef64c69375"
  }
}
